.coveragerc
LICENSE
MANIFEST.in
README.md
setup.cfg
setup.py
tox.ini
hhpp/__init__.py
hhpp.egg-info/PKG-INFO
hhpp.egg-info/SOURCES.txt
hhpp.egg-info/dependency_links.txt
hhpp.egg-info/top_level.txt
hhpp/llive/__init__.py
hhpp/llive/fallbacks.py
test/__init__.py
test/llive/__init__.py
test/llive/test_fallbacks.py